mumot/__init__.py
mumot/consts.py
mumot/controllers.py
mumot/defaults.py
mumot/exceptions.py
mumot/models.py
mumot/utils.py
mumot/views.py
mumot-1.2.2.dist-info/LICENSE
mumot-1.2.2.dist-info/METADATA
mumot-1.2.2.dist-info/WHEEL
mumot-1.2.2.dist-info/top_level.txt
mumot-1.2.2.dist-info/RECORD
