Metadata-Version: 2.1
Name: mumot
Version: 1.2.2
Summary: Multiscale Modelling Tool
Home-page: https://github.com/DiODeProject/MuMoT
Author: James A. R. Marshall, Andreagiovanni Reina, Thomas Bose
Author-email: james.marshall@shef.ac.uk
License: GPL-3.0
Platform: UNKNOWN
Classifier: License :: OSI Approved :: GNU General Public License v3 (GPLv3)
Classifier: Operating System :: OS Independent
Classifier: Programming Language :: Python
Classifier: Programming Language :: Python :: 3.6
Classifier: Programming Language :: Python :: 3.7
Classifier: Programming Language :: Python :: 3.8
Classifier: Topic :: Scientific/Engineering
Classifier: Topic :: Scientific/Engineering :: Chemistry
Classifier: Topic :: Scientific/Engineering :: Mathematics
Classifier: Topic :: Scientific/Engineering :: Physics
Requires-Dist: antlr4-python3-runtime (<4.8,>=4.7)
Requires-Dist: graphviz
Requires-Dist: setuptools
Requires-Dist: ipykernel
Requires-Dist: ipython (>=7.10.0)
Requires-Dist: ipywidgets
Requires-Dist: matplotlib
Requires-Dist: networkx
Requires-Dist: notebook
Requires-Dist: pydstool (>=0.90.3)
Requires-Dist: pyzmq
Requires-Dist: scipy
Requires-Dist: sympy (<1.5,>=1.4)
Requires-Dist: tornado
Provides-Extra: docs
Requires-Dist: sphinx ; extra == 'docs'
Provides-Extra: test
Requires-Dist: pytest ; extra == 'test'
Requires-Dist: pytest-cov ; extra == 'test'
Requires-Dist: nbval (>=0.9.5) ; extra == 'test'
Requires-Dist: nbdime ; extra == 'test'
Requires-Dist: jupyter ; extra == 'test'
